py_wavegenerator_native-0.1.3.dist-info/METADATA
py_wavegenerator_native-0.1.3.dist-info/WHEEL
py_wavegenerator_native/__init__.py
py_wavegenerator_native/py_wavegenerator_native.cpython-312-darwin.so
py_wavegenerator_native-0.1.3.dist-info/RECORD
