Metadata-Version: 2.4
Name: py_wavegenerator_native
Version: 0.1.3
Summary: 波形生成器模块 - Python波形生成和信号处理库
Author: Admin <admin@example.com>
Author-email: Admin <admin@example.com>
License: MIT
Project-URL: Source Code, https://github.com/example/py_wavegenerator
